scm_helper/__init__.py
scm_helper/api.py
scm_helper/browser.py
scm_helper/coach.py
scm_helper/conduct.py
scm_helper/config.py
scm_helper/crypto.py
scm_helper/default.py
scm_helper/entity.py
scm_helper/facebook.py
scm_helper/file.py
scm_helper/files.py
scm_helper/groups.py
scm_helper/gui.py
scm_helper/ipad.py
scm_helper/issue.py
scm_helper/license.py
scm_helper/lists.py
scm_helper/main.py
scm_helper/member.py
scm_helper/members.py
scm_helper/notify.py
scm_helper/parent.py
scm_helper/records.py
scm_helper/roles.py
scm_helper/sendmail.py
scm_helper/sessions.py
scm_helper/swimmer.py
scm_helper/version.py
scm_helper-2.0.3.dist-info/LICENSE.md
scm_helper-2.0.3.dist-info/METADATA
scm_helper-2.0.3.dist-info/WHEEL
scm_helper-2.0.3.dist-info/entry_points.txt
scm_helper-2.0.3.dist-info/top_level.txt
scm_helper-2.0.3.dist-info/RECORD
