Metadata-Version: 2.1
Name: scm_helper
Version: 2.0.3
Summary: Helper tool to manage data in Swim Club Manager
Home-page: https://github.com/ColinRobbins/scm-helper
Author: Colin Robbins
Author-email: colin.john.robbins@gmail.com
Project-URL: Bug Tracker, https://github.com/ColinRobbins/scm-helper/issues
Project-URL: Documentation, https://github.com/ColinRobbins/scm-helper/wiki
Project-URL: Source Code, https://github.com/ColinRobbins/scm-helper
Project-URL: Change Log, https://github.com/ColinRobbins/scm-helper/blob/master/CHANGELOG.md
Classifier: Programming Language :: Python :: 3
Classifier: License :: OSI Approved :: MIT License
Classifier: Operating System :: OS Independent
Requires-Python: >=3.7
License-File: LICENSE.md
Requires-Dist: schema >=0.7.2
Requires-Dist: requests >=2.22.0
Requires-Dist: pyyaml >=5.3
Requires-Dist: cryptography >=2.8
Requires-Dist: func-timeout >=4.3.5
Requires-Dist: selenium >=4.12.0
Requires-Dist: parse >=1.20.2
